{
 "absolute_value": 0,
 "align_labels_right": 0,
 "creation": "2022-04-26 14:01:32.640949",
 "css": "/*.print-format {<br> <div class=\"letter-head\">{{ letter_head }}</div>*/\n/*<!--{%- endif %}{%- endif %*/\n/*  margin-left: 9mm;*/\n/*  margin-right: 5mm;*/\n/*  margin-bottom: 5mm;*/\n/*}*/\n\n/*.print-format {*/\n/*    font-size: 8pt;*/\n/*    padding: 0.1in;*/\n/*}*/\n\n.print-format td{\n    padding: 0px!important;\n    border-spacing: 0!important;\n    margin-left:5mm; \n    margin-right:5mm;\n    margin-top:5mm;\n    margin-bottom:5mm;\n    height:0!important;\n    padding-left: 2px!important;\n}\n* {\n  box-sizing: border-box;\n}\n/* Create three unequal columns that floats next to each other */\n.column {\n  float: left;\n  /*height: 100px;*/ /* Should be removed. Only for demonstration*/\n}\n.left {\n  width: 73%!important;\n}\n.right {\n  width: 27%!important;\n  border-left:1px solid black;\n}\ntable .t1{\n  width: 100%;\n  border: 1px solid;\n  font-size:10px!important;\n}\n\n.t1 td{\n    width:25%;\n   \n    padding: 0!important; border-spacing: 0!important;  margin:0!important;\n}\n.tl{\n    border-left:1px solid black;\n    \n}\n.tr{\n    border-right:1px solid black;\n    \n}\n\n.itemth{\n    \n    border-top: 1px solid black;\n    border-left: 1px solid black;\n    border-bottom: 1px solid black;\n    text-align:center;\n}\n.itemtd{\n    border-left: 1px solid black;\n    padding: 0px!important; border-spacing: 0!important;  margin:0!important; height:0!important;padding-left: 2px!important;\n}\n.page{\n    border: 2px solid black;\n    width: 100%;\n    /*height: 1005px;*/\n}\n.itemth1{\n    /*border-top: 1px solid black;*/\n    /*border-left: 1px solid black;*/\n    border-bottom: 1px solid black;\n    text-align:center;\n}\n\n.letter-head{\n    margin-top:-30px;\n}\n\n",
 "custom_format": 1,
 "default_print_language": "en-GB",
 "disabled": 0,
 "doc_type": "Sales Invoice",
 "docstatus": 0,
 "doctype": "Print Format",
 "font": "Default",
 "html": "\n\n{% set serial_no=[] %}\n{% set page_no=[] %}\n{% set tablen=9 %}\n{% set items = doc.items %}\n{% set tax = [] %}\n{% set tax1 = [] %}\n{% set taxcal={} %}\n{% set itaxcal={} %}\n{% set sepitems=[] %}\n{% for i in range((items|length)//tablen) %}\n\n    {% set sep1=[] %}\n    {% for j in range(i*tablen, i*tablen +tablen) %}\n        {% set sep=[] %}\n    {% set _= sep.append(items[j].item_name) %}\n    {% set _= sep.append(items[j].gst_hsn_code) %}\n    {% set d=frappe.get_doc('Item',items[j].item_code) %}\n    {% set _= sep.append(items[j].qty) %}\n    {% set _= sep.append(items[j].rate) %}\n    {% set _= sep.append(items[j].discount_percentage) %}\n    {% set _= sep.append(items[j].amount) %}\n    {% if doc.taxes_and_charges==\"INSTATE GST\" or doc.taxes_and_charges==\"OUTSTATE GST\" %}\n                    {% set d=frappe.get_doc('Item',items[j].item_code) %}\n                    {% if d.taxes|length != 0 %}\n                    {% set t=d.taxes[0].item_tax_template %}\n                    {% set td=frappe.get_doc('Item Tax Template',t) %}\n                   \n                    {% for i in td.taxes %}\n                    {% set k=tax.append(i.tax_rate) %}\n                    {% endfor %}\n                    {% set s1= sep.append(tax[tax|length -1]+tax[tax|length -2]) %}\n                    {% set taxx = tax[tax|length -1]+tax[tax|length -2] %}\n                    {% if taxx in taxcal %}\n                        {% set x=[] %}\n                        {% set _=x.append(taxcal[taxx]) %}\n                        {% set _= taxcal.update({taxx: x[0]+ items[j].amount})%}\n                    {% else %}\n                    {% set _=taxcal.update({taxx: items[j].amount}) %}\n                    {% endif %}\n                    {% else %}\n                    {% set s1= sep.append(0) %}\n                    {% endif %}\n                    \n   \n    {% else %}\n     {% set _= sep.append(0) %}\n    \n    {% endif %}\n    {% set _= sep.append(items[j].amount) %}\n    {% set _ = sep1.append(sep) %}\n    {% endfor %}\n    {% set _ = sepitems.append(sep1) %}\n{% endfor %}\n\n{% set sep1=[] %}\n{% for j in range((items|length)//tablen *tablen, items|length) %}\n    {% set sep=[] %}\n    {% set _= sep.append(items[j].item_name) %}\n    {% set _= sep.append(items[j].gst_hsn_code) %}\n    {% set d=frappe.get_doc('Item',items[j].item_code) %}\n    {% set _= sep.append(items[j].qty) %}\n    {% set _= sep.append(items[j].rate) %}\n    {% set _= sep.append(items[j].discount_percentage) %}\n    {% set _= sep.append(items[j].amount) %}\n    \n    {% if doc.taxes_and_charges==\"INSTATE GST\" or doc.taxes_and_charges==\"OUTSTATE GST\" %}\n                    {% set d=frappe.get_doc('Item',items[j].item_code) %}\n                    {% if d.taxes|length != 0 %}\n                    {% set t=d.taxes[0].item_tax_template %}\n                    {% set td=frappe.get_doc('Item Tax Template',t) %}\n                   \n                    {% for i in td.taxes %}\n                    {% set k=tax.append(i.tax_rate) %}\n                    {% endfor %}\n                    {% set s1= sep.append(tax[tax|length -1]+tax[tax|length -2]) %}\n                    {% set taxx = tax[tax|length -1]+tax[tax|length -2] %}\n                    {% if taxx in taxcal %}\n                        {% set x=[] %}\n                        {% set _=x.append(taxcal[taxx]) %}\n                        {% set _= taxcal.update({taxx: x[0]+ items[j].amount})%}\n                    {% else %}\n                    {% set _=taxcal.update({taxx: items[j].amount}) %}\n                    {% endif %}\n                    {% else %}\n                    {% set s1= sep.append(0) %}\n                    {% endif %}\n                    \n    {% else %}\n     {% set _= sep.append(0) %}\n    \n    {% endif %}\n    \n   \n    {% set _= sep.append(items[j].amount) %}\n    {% set _ = sep1.append(sep) %}\n{% endfor %}\n{% if sep1 != [] %}\n    {% set _ = sepitems.append(sep1) %}   \n{% endif %}\n\n\n{% set hsnwisetaxes = [] %}\n{% set hsn={} %}\n{% for item in sepitems %}\n    \n{% endfor %}\n\n{% if letter_head and not no_letterhead -%}\n{% if print_settings.repeat_header_footer %}\n   <br> <div class=\"letter-head\">{{ letter_head }}</div>\n{%- endif %}\n{%- endif %}\n\n<div class=\"page\" style=\"font-size:10px;font-family: Arial;margin-top:-5mm\">\n\n    \n        <table style=\"width:100%;font-size:10px;margin-bottom:-8mm;\">\n            <tr><td colspan=\"4\" style=\"text-align:center ;vertical-align: middle;font-size:12px;height:20px!important;padding-top:5px!important;\"><b>COMMERCIAL INVOICE</b></td></tr>\n            <tr style=\"background-color: #dddddd; border-top:1px solid black;\"><td style=\"width:25%;\">Invoice</td><td class='tr' style=\"width:25%;\">:{{doc.name}}</td>\n                <td style=\"width:25%;\">Dc No</td><td style=\"width:25%;\">:{% if frappe.db.get_value(\"Delivery Note\", {\"name\": doc.items[0].delivery_note}, \"name\") != None%}{{frappe.db.get_value(\"Delivery Note\", {\"name\": doc.items[0].delivery_note}, \"name\")}}{% endif %}</td></tr>\n            <tr><td style=\"width:25%;\">Date/Time</td><td class='tr' style=\"width:25%;\">:{{doc.get_formatted(\"posting_date\")}}</td>\n                <td style=\"width:25%;\">Payment Terms</td><td style=\"width:25%;\">:{% if doc.payment_terms_template %}{{doc.payment_terms_template}}{% endif %}</td></tr>\n            <tr style=\"background-color: #dddddd;\"><td style=\"width:25%;\">Cust. PO No. </td><td class='tr' style=\"width:25%;\">:{% if doc.po_no %} {{doc.po_no}} {% endif %} </td>\n                <td style=\"width:25%;\">Cust. PO. Date. </td><td style=\"width:25%;\">:{% if doc.get_formatted(\"po_date\") %} {{doc.get_formatted(\"po_date\")}} {% endif %}</td></tr>\n            \n             <tr><td style=\"width:25%;\">Cust. Contact  </td><td class='tr' style=\"width:25%;\">:\n                 {% if doc.posa_notes %}\n                    {{ doc.posa_notes }}\n                 {% elif doc.delivery_perosn_name %}\n                    {{ doc.delivery_perosn_name }}\n                 {% else %}\n                    {% set cust_doc = frappe.get_doc('Customer', doc.customer) %}\n                    {% if cust_doc.name_of_mgr %}\n                        {{cust_doc.name_of_mgr}}\n                    {% endif %} \n                    {% if cust_doc.phone_no %} \n                        / {{cust_doc.phone_no}}\n                    {% endif %}\n                {% endif %}\n                </td>\n                <td style=\"width:25%;\">Sales Contact</td><td style=\"width:25%;\">:</td></tr>\n            {% set cus=frappe.get_doc('Customer',doc.customer) %}\n            \n            <tr style=\"background-color: #dddddd;\"><td style=\"width:25%;\">Cust. Email  </td><td class='tr' style=\"width:25%;\">:{% if cus.email_id %} {{cus.email_id}} {% endif %}</td>\n                <td style=\"width:25%;\">Despatched Through  </td><td style=\"width:25%;\">:{{doc.mode_of_transport}}</td></tr>\n            <tr><td style=\"width:25%;\">Shipping Terms  </td><td class='tr' style=\"width:25%;\">:{% if doc.shipping_rule %} {{doc.shipping_rule}} {% endif %} </td>\n                <!--<td style=\"width:25%;\">Service Report No. </td><td style=\"width:25%;\">:{{\"\"}}</td></tr>-->\n            <tr><td colspan=\"4\" style=\"text-align:center;border-top:1px solid black;border-bottom:1px solid black;height:15px!important;\"></td></tr>\n            \n            <tr style=\"background-color: #dddddd;\"><td style=\"border-bottom:1px solid black;height:17px!important;padding:5px!important;\">BILL TO:</td><td style=\"border-bottom:1px solid black;height:17px!important;padding:5px!important;\"></td><td style=\"border-bottom:1px solid black;border-left:1px solid black;height:17px!important;padding:5px!important;\">SHIP TO:</td><td style=\"border-bottom:1px solid black;height:17px!important;padding:5px!important;\"></td></tr>\n            <tr style=\"width:50%;\"><td><b>{{doc.customer_name}}</b><br>{{doc.address_display or \" \"}}</td><td class='tr' style=\"width:25%;\"></td>\n                <td style=\"width:25%;\"><b>{{doc.customer_name}}</b><br><span style=\" font-size:10px!important;\">{% if doc.shipping_address %}{{doc.shipping_address or \" \"}}{%else%}{{doc.address_display or \" \"}}{% endif %}</span></td><td style=\"width:25%;\"></td></tr>\n        </table>\n        <table class='itemtable' style=\"font-size:10px;font-family: Arial;\">\n            <tr style='border-bottom:1px solid black; height: 5px!important;'>\n                <td class='itemth' style='border-left:0;width:1%;background-color: #dddddd;'><span style=\"font-weight: bold;font-size:10px !important;\">SI<br>No.</span></td>\n                <th class='itemth' style=\"width:355px\">Description of Goods</th>\n                <th class='itemth' >HSN</th>\n                <th class='itemth' >Qty</th>\n                <th class='itemth' >Rate</th>\n                {% if doc.discount_amount %}\n                    <th class='itemth'>Disc %</th>\n                {% endif %}\n                <th class='itemth' >Taxable<br>Amt</th>\n                <th class='itemth'>GST</th>\n                <th class='itemth' >Amount</th>\n            </tr>\n            \n            {% for item in doc.items %}\n                {% set _=serial_no.append(1) %}\n                <tr>\n                    <td class='itemtd' style='border-left:0; text-align:center'>{{ serial_no|length }}</td>\n                    <td class='itemtd' style=\"text-align:left\">{{ item.item_code }}</td>\n                    <td class='itemtd' style=\"text-align:center;\">{{ item.gst_hsn_code }}</td>\n                    <td class='itemtd' style=\"text-align:center;\">{{ \"%d\"|format(item.qty)}}</td>\n                    <td class='itemtd' style=\"text-align:center\">{{ \"%.2f\"|format(item.rate) }}</td>\n                    {% if doc.discount_amount %}\n                        <td class='itemtd' style=\"text-align:center\"> \n                                 {% if item[6] %}\n                                {{ item.discount_percentage }}\n                            {% else %}{{ 0 }} {% endif %}\n                        </td>\n                    {% endif %}\n                    <!--<td class='itemtd' style=\"text-align:center\">-->\n                    <!--    {% if item.discount_percentage != \"0\" %}-->\n                    <!--        {{ item.discount_percentage }}-->\n                    <!--    {% else %} {% endif %}</td>-->\n                    <td class='itemtd'  style='text-align:center'>{{ \"%.2f\"|format(item.amount) }}</td>\n                    {% if doc.taxes_and_charges==\"INSTATE GST\" or doc.taxes_and_charges==\"OUTSTATE GST\" %}\n                        {% set d=frappe.get_doc('Item',item.item_code) %}\n                        {% if d.taxes|length != 0 %}\n                            {% set t=d.taxes[0].item_tax_template %}\n                            {% set td=frappe.get_doc('Item Tax Template',t) %}\n                            {% set tax=[] %}\n                            {% for i in td.taxes %}\n                                {% set _=tax.append(i.tax_rate) %}\n                            {% endfor %}\n                        {% endif%}\n                        {% set d1=frappe.get_doc('Item',item.item_code) %}\n                        {% if d.taxes|length != 0 %}\n                            {% set t1=d1.taxes[0].item_tax_template %}\n                            {% set td1=frappe.get_doc('Item Tax Template',t1) %}\n                            {% set tax1=[] %}\n                            {% for i in td1.taxes %}\n                                {% set _=tax1.append(i.tax_rate) %}\n                            {% endfor %}\n                            <td class='itemtd' style=\"text-align:center;\">{{ \"%d\"|format(tax[0]*2) }}{{'%'}}</td>\n                        {% else %}\n                            <td class='itemtd' style=\"text-align:right;\">{{\"\"}}</td>\n                        {% endif %}\n                    {% else %}\n                        <td class='itemtd' style=\"text-align:right;\">{{\"\"}}</td>\n                    {% endif %}\n                    <td class='itemtd' style='height:20px!important;text-align:right;'>{{ \"%.2f\"|format(item.amount) }}</td>\n\n                    \n                </tr>\n            {% endfor %}\n            {% for empty in range(10- doc.items|length) %}\n                <tr style=\"height:10px;\">\n                    <td class='itemtd' style='border-left:0; text-align:center'></td>\n                    <td class='itemtd' style=\"text-align:left\"></td>\n                    <td class='itemtd' style=\"text-align:center;\"></td>\n                    <td class='itemtd' style=\"text-align:center;\"></td>\n                    <td class='itemtd' style=\"text-align:center\"></td>\n                    {% if doc.discount_amount %}\n                        <td class='itemtd' style=\"text-align:center\"></td>\n                    {% endif %}\n                    <td class='itemtd'  style='text-align:center'></td>\n                   <td class='itemtd' style=\"text-align:center;\"></td>\n                   <td class='itemtd' style='height:20px!important;text-align:right;'></td>\n                </tr>\n            {% endfor %}\n            <br>\n            <br>\n            <tr style='border-bottom:1px solid black;border-top:1px solid black;height:20px!important;'><td></td>\n            <td style=\"text-align:right;border-right:1px solid black;padding-right:5px!important;;\">Total</td>\n            <td style=\"text-align:right;border-right:1px solid black;\"></td>\n            <td style=\"text-align:center;border-right:1px solid black;\">{{doc.total_qty}}</td>\n            <td style=\"text-align:right;border-right:1px solid black;\"></td>\n            {% if doc.discount_amount %}\n                <td style=\"text-align:center;border-right:1px solid black;\">{{ doc.additional_discount_percentage }}</td>\n            {% endif %}\n            <td style=\"text-align:center;border-right:1px solid black;\">{{doc.total}}</td>\n            <td style=\"text-align:right;border-right:1px solid black;\"></td>\n            <td style=\"text-align:right;border-right:1px solid black;\">{{doc.total}}</td>\n            </tr>\n            <tr><td colspan=\"9\" style=\"padding-left:5px!important;border-bottom:1px solid black;height:20px!important;\">In Words: {{doc.in_words[3:]}}</td></tr>\n            \n            \n        </table>\n        \n        <div class=\"column left\" style=\"position: relative\">\n            <table style=\"width:100%;font-size:10px!important;\">\n            <tr style='border-bottom:1px solid black; height: 0px!important;'>\n            <th  class='itemth1' style=\"border-left:0;align:center;\">GST Rate</th>\n            <th style=\"align:center;\">Taxable Values</th>\n            <th class='itemth1' style=\"align:center;\">Central Tax</th>\n            <th class='itemth1' style=\"align:center;\">State Tax</th>\n            </tr>\n            {% for i in taxcal %}\n            <tr>\n                <td style=\"text-align:center;width:25%;\">{{(i)|int}}%</td>\n                <td style=\"text-align:center;\">{{doc.net_total}}</td>\n                <td style=\"width:25%;text-align:center;\"><span style=\"text-align:left;padding-left:18px!important;\"><b>{{(i/2) |int}}%</b></span><span style=\"float:right;padding-right:18px!important;\">{{doc.total_taxes_and_charges/2 }}</span></td>\n                <td style=\"width:25%;text-align:center;\"><span style=\"text-align:left;padding-left:18px!important;\"><b>{{(i/2) |int}}%</b></span><span style=\"float:right;padding-right:18px!important;\">{{doc.total_taxes_and_charges/2}}</span></td>\n            </tr>\n            {% endfor %}\n            <tr style=\"border-top:1px solid black;\">\n                <td style=\"width:25%;text-align:center;\"><b>Total in INR</b></td>\n                <td style=\"text-align:center;width:25%;padding-right:2px!important;\"><b>{{doc.net_total}}</b></td>\n                <td style=\"text-align:right;width:25%;padding-right:14px!important;\"><b>{{doc.total_taxes_and_charges/2 }}</b></td>\n                <td style=\"text-align:right;width:25%!;padding-right:14px!important;\"><b>{{doc.total_taxes_and_charges/2}}</b></td>\n            </tr>\n            </table> \n        </div>\n        <div class=\"column right\" style=\"position: relative\">\n            <table style=\"width:100%;\">\n            {% if doc.discount_amount %}\n                <tr style='height:20px!important;font-size:10px;font-family: Arial;'>\n                <td class='itemth1' style=\"width:15%;border-right:1px solid black;text-align:right;\">Discount</td>\n                <td class='itemth1' style=\"width:12%;text-align:right;\">{{doc.discount_amount}}</td>\n                </tr>\n            {% endif %}\n            <tr style='height:20px!important;font-size:10px;font-family: Arial;'>\n            <td class='itemth1' style=\"width:15%;border-right:1px solid black;text-align:right;\">Subtotal</td>\n            <td class='itemth1' style=\"width:12%;text-align:right;\">{{doc.net_total}}</td>\n            </tr>\n            {% if doc.taxes_and_charges==\"INSTATE GST\" %}\n            <tr style='border-bottom:1px solid black;height:20px!important;'>\n            <td class='itemth1' style=\"width:15%;border-right:1px solid black;text-align:right;font-size:10px;font-family: Arial;\">Add: CGST</td>\n            <td class='itemth1' style=\"width:12%;text-align:right;\">{{doc.total_taxes_and_charges/2}}</td>\n            </tr>\n            <tr style='border-bottom:1px solid black;height:20px!important;'>\n            <td class='itemth1' style=\"width:15%;border-right:1px solid black;text-align:right;font-size:10px;font-family: Arial;\">Add: SGST</td>\n            <td class='itemth1' style=\"width:12%;text-align:right;\">{{doc.total_taxes_and_charges/2}}</td>\n            </tr>\n            <tr style='border-bottom:1px solid black;height:20px!important;'>\n            <td class='itemth1' style=\"width:15%;border-right:1px solid black;text-align:right;\">Add: IGST</td>\n            <td class='itemth1' style=\"width:12%;text-align:right;\">{{\"-\"}}</td>\n            </tr>\n            {% elif doc.taxes_and_charges==\"OUTSTATE GST\" %}\n            <tr style='border-bottom:1px solid black;height:20px!important;'>\n            <td class='itemth1' style=\"width:15%;border-right:1px solid black;text-align:right;border-left:1px solid black;\">Add: CGST</td>\n            <td class='itemth1' style=\"width:12%;text-align:right;\">{{\"-\"}}</td>\n            </tr>\n            <tr style='border-bottom:1px solid black;height:20px!important;'>\n            <td class='itemth1' style=\"width:15%;border-right:1px solid black;text-align:right;border-left:1px solid black;\">Add: SGST</td>\n            <td class='itemth1' style=\"width:12%;text-align:right;\">{{\"-\"}}</td>\n            </tr>\n            <tr style='border-bottom:1px solid black;height:20px!important;'>\n            <td class='itemth1' style=\"width:15%;border-right:1px solid black;text-align:right;border-left:1px solid black;\">Add: IGST</td>\n            <td class='itemth1' style=\"width:12%;text-align:right;\">{{doc.total_taxes_and_charges}}</td>\n            </tr>\n            {% else %}\n                <tr style='border-bottom:1px solid black;height:20px!important;'>\n            <td class='itemth1' style=\"width:15%;border-right:1px solid black;text-align:right;border-left:1px solid black;\">Add: CGST</td>\n            <td class='itemth1' style=\"width:12%;text-align:right;\">{{\"-\"}}</td>\n            </tr>\n            <tr style='border-bottom:1px solid black;height:20px!important;'>\n            <td class='itemth1' style=\"width:15%;border-right:1px solid black;text-align:right;border-left:1px solid black;\">Add: SGST</td>\n            <td class='itemth1' style=\"width:12%;text-align:right;\">{{\"-\"}}</td>\n            </tr>\n            <tr style='border-bottom:1px solid black;height:20px!important;'>\n            <td class='itemth1' style=\"width:15%;border-right:1px solid black;text-align:right;border-left:1px solid black;\">Add: IGST</td>\n            <td class='itemth1' style=\"width:12%;text-align:right;\">{{\"-\"}}</td>\n            </tr>\n            {% endif %}\n            <tr style='height:20px!important;'>\n            <td class='itemth1' style=\"width:15%;border-right:1px solid black;text-align:right;font-size:10px;\"><b>Total Amount in INR</b></td>\n            <td class='itemth1' style=\"width:12%;text-align:right;\"><b>{{doc.rounded_total}}</b></td>\n            </tr>\n        </table>\n       \n        \n</div>\n<table style=\"width:100%; border-top:1px solid black;\"><tr><td></td></tr></table>\n<table  style=\"width:70%;float:left;border-right:1px solid black;\">\n    <tr>\n        <td><b>Terms and Conditions</b></td> \n    </tr>\n   <tr>\n       <td>\n           <div>\n            {{ doc.terms or \" \" }}\n          </div>\n       </td>\n   </tr>\n</table>\n<table style=\"width:30%;font-size:10px;font-family: Arial;float:left; \">\n    <tr>\n    <td colspan=2><b>Bank Details</b></td>\n    </tr>\n    <tr>\n    {% set bank = frappe.get_doc(\"Bank Account\", \"Sri Kumaran SuperStore - ICICI\")%}\n    <td style=\"width:50%;\">BANK</td><td style=\"width:50%;\">:{{bank.bank or \" \"}}</td>\n    </tr>\n    <tr>\n        <td>ACCOUNT NAME</td><td>:{{bank.account_name or \" \"}}</td>\n    </tr>\n    <tr>\n        <td>A/C NUMBER</td><td>:{{bank.bank_account_no or \" \"}}</td>\n    </tr>\n    <tr>\n        <td>IFSC CODE </td><td>:{{bank.branch_code or \" \"}}</td>\n    </tr>\n    <tr>\n        <td>BRANCH</td><td>:{{bank.branch or \" \"}}</td>\n    </tr>\n    \n    </table>\n\n<table class=\"table table-condensed border-primary\" style=\"top:-5mm;position:relative;width:100%;font-size:10px;font-family: Arial;border-top:1px solid black;border-bottom:1px solid black;\">\n              \n                <td style=\"tex-align:center; border:1px solid black; width:50%;\"><b>Outstanding Details</b>\n                <table style=\"width:100%;font-size:10px;font-family: Arial;\"><tr>\n                        <td>PREVIOUS BALANCE  :{{ doc.outstandingamount|int }}</td>\n                        <td>CURRENT INVOICE  :{{ (doc.outstanding_amount) | int}}</td>\n                            {% set preoutstanding = doc.outstandingamount | int %}\n                            {% set out=(doc.outstanding_amount + preoutstanding) | int %}\n                        <td>TOTAL OUTSTANDING  :{{ out }}</td> \n                    </tr>\n                    </table>\n                </td>\n            </tr>\n        </table>\n        <table style=\"text-align:center;width:100%;margin-top:20px;font-size:10px;font-family: Arial;\">\n            <tr><td height:100px>__________________</td><td>__________________</td><td>__________________</td><td>_________________________</td></tr>\n            <tr><td>Customer Sign</td><td>Prepared By</td><td>Checked By</td><td>Authorized Signatory</td></tr>\n        </table>\n</div>\n    <div class=\"page-break\"></div>\n\n",
 "idx": 0,
 "line_breaks": 0,
 "modified": "2022-04-26 14:42:33.324525",
 "modified_by": "Administrator",
 "module": "sks",
 "name": "TS Commercial Invoice with Discount",
 "owner": "Administrator",
 "print_format_builder": 0,
 "print_format_type": "Jinja",
 "raw_printing": 0,
 "show_section_headings": 0,
 "standard": "Yes"
}