{
 "creation": "2022-07-11 13:02:30.812050",
 "docstatus": 0,
 "doctype": "Number Card",
 "filters_json": "{\"from_date\":\"2022-07-11\",\"to_date\":\"2022-07-11\",\"employee\":\"navin@gmail.com\"}",
 "function": "Count",
 "idx": 0,
 "is_public": 0,
 "is_standard": 1,
 "label": "Credit Sales Amount Today -Userwise",
 "modified": "2022-07-11 13:02:30.849376",
 "modified_by": "navin@gmail.com",
 "module": "sks",
 "name": "Credit Sales Amount Today -Userwise-1",
 "owner": "navin@gmail.com",
 "report_field": "outstanding_amount",
 "report_function": "Sum",
 "report_name": "Thirvu Userwise - Selling Module_1",
 "show_percentage_stats": 1,
 "stats_time_interval": "Daily",
 "type": "Report"
}